yaycl/__init__.py
yaycl-0.3.0.dist-info/DESCRIPTION.rst
yaycl-0.3.0.dist-info/METADATA
yaycl-0.3.0.dist-info/RECORD
yaycl-0.3.0.dist-info/WHEEL
yaycl-0.3.0.dist-info/entry_points.txt
yaycl-0.3.0.dist-info/metadata.json
yaycl-0.3.0.dist-info/pbr.json
yaycl-0.3.0.dist-info/top_level.txt
