Metadata-Version: 2.0
Name: yaycl
Version: 0.3.0
Summary: YAML Config Autoloader
Home-page: https://github.com/seandst/yaycl
Author: Sean myers
Author-email: semyers@redhat.com
License: MIT
Platform: UNKNOWN
Classifier: Development Status :: 4 - Beta
Classifier: Environment :: Console
Classifier: Intended Audience :: Developers
Classifier: Intended Audience :: Information Technology
Classifier: License :: OSI Approved :: MIT License
Classifier: Operating System :: OS Independent
Classifier: Programming Language :: Python
Classifier: Programming Language :: Python :: 2.7
Classifier: Programming Language :: Python :: 3
Requires-Dist: layered-yaml-attrdict-config
Requires-Dist: wheel
